biox/__init__.py
biox/core.py
bioxai-0.0.2.dist-info/METADATA
bioxai-0.0.2.dist-info/WHEEL
bioxai-0.0.2.dist-info/licenses/LICENSE
bioxai-0.0.2.dist-info/RECORD
