Metadata-Version: 2.4
Name: bioxai
Version: 0.0.2
Summary: BioX: A foundation for reproducible bioinformatics tooling
Project-URL: Homepage, https://github.com/takshan/biox
Project-URL: Documentation, https://github.com/takshan/biox#readme
Project-URL: Source, https://github.com/takshan/biox
Project-URL: Issues, https://github.com/takshan/biox/issues
Project-URL: Changelog, https://github.com/takshan/biox/blob/main/CHANGELOG.md
Author-email: Rahulk Brahma <rahu.brahma@uni-greifswald.de>
Maintainer-email: Rahulk Brahma <rahu.brahma@uni-greifswald.de>
License: MIT License
License-File: LICENSE
Keywords: bioinformatics,biology,biox,science,toolkit
Classifier: Development Status :: 3 - Alpha
Classifier: Intended Audience :: Science/Research
Classifier: License :: OSI Approved :: MIT License
Classifier: Programming Language :: Python
Classifier: Programming Language :: Python :: 3
Classifier: Programming Language :: Python :: 3 :: Only
Classifier: Programming Language :: Python :: 3.9
Classifier: Programming Language :: Python :: 3.10
Classifier: Programming Language :: Python :: 3.11
Classifier: Programming Language :: Python :: 3.12
Classifier: Topic :: Scientific/Engineering :: Bio-Informatics
Requires-Python: >=3.9
Provides-Extra: dev
Requires-Dist: build>=1.2; extra == 'dev'
Requires-Dist: coverage>=7.4; extra == 'dev'
Requires-Dist: mypy>=1.10; extra == 'dev'
Requires-Dist: pre-commit>=3.7; extra == 'dev'
Requires-Dist: pytest>=8.0; extra == 'dev'
Requires-Dist: ruff>=0.6; extra == 'dev'
